craft/__init__.py
craft/craft_tf.py
craft/craft_torch.py
craft/utils.py
craft/optim/__init__.py
craft/optim/implicit_diff.py
craft/optim/nmf.py
craft/optim/nnls.py
craft/sobol/__init__.py
craft/sobol/estimators.py
craft/sobol/sampler.py
Craft_xai-0.0.3.dist-info/LICENSE
Craft_xai-0.0.3.dist-info/METADATA
Craft_xai-0.0.3.dist-info/WHEEL
Craft_xai-0.0.3.dist-info/top_level.txt
Craft_xai-0.0.3.dist-info/RECORD
